BlackBoxAuditing/BlackBoxAuditor.py
BlackBoxAuditing/GradientFeatureAuditor.py
BlackBoxAuditing/__init__.py
BlackBoxAuditing/audit_reading.py
BlackBoxAuditing/consistency_graph.py
BlackBoxAuditing/data.py
BlackBoxAuditing/disparate_impact.py
BlackBoxAuditing/disparate_impact_evaluator.py
BlackBoxAuditing/histogram_maker.py
BlackBoxAuditing/kddtests.py
BlackBoxAuditing/loggers.py
BlackBoxAuditing/make_graphs.py
BlackBoxAuditing/measurements.py
BlackBoxAuditing/repair.py
BlackBoxAuditing/run_test_suite.sh
BlackBoxAuditing/splitters.py
BlackBoxAuditing/test.py
BlackBoxAuditing/MATLAB_code/LICENSE.txt
BlackBoxAuditing/MATLAB_code/README.md
BlackBoxAuditing/MATLAB_code/check_installation.m
BlackBoxAuditing/MATLAB_code/testSLIM.m
BlackBoxAuditing/MATLAB_code/test_file.data
BlackBoxAuditing/MATLAB_code/writeData.m
BlackBoxAuditing/experiments/__init__.py
BlackBoxAuditing/experiments/DRP/__init__.py
BlackBoxAuditing/experiments/DRP/example_headers.py
BlackBoxAuditing/experiments/DRP/load_data.py
BlackBoxAuditing/experiments/adult/__init__.py
BlackBoxAuditing/experiments/adult/load_data.py
BlackBoxAuditing/experiments/arrests/__init__.py
BlackBoxAuditing/experiments/arrests/converter.py
BlackBoxAuditing/experiments/arrests/load_data.py
BlackBoxAuditing/experiments/diabetes/__init__.py
BlackBoxAuditing/experiments/diabetes/load_data.py
BlackBoxAuditing/experiments/german/__init__.py
BlackBoxAuditing/experiments/german/load_data.py
BlackBoxAuditing/experiments/glass/__init__.py
BlackBoxAuditing/experiments/glass/load_data.py
BlackBoxAuditing/experiments/ricci/__init__.py
BlackBoxAuditing/experiments/ricci/load_data.py
BlackBoxAuditing/experiments/sample/__init__.py
BlackBoxAuditing/experiments/sample/load_data.py
BlackBoxAuditing/experiments/sample_2/__init__.py
BlackBoxAuditing/experiments/sample_2/load_data.py
BlackBoxAuditing/find_contexts/__init__.py
BlackBoxAuditing/find_contexts/context_finder.py
BlackBoxAuditing/find_contexts/expand_and_find_contexts.py
BlackBoxAuditing-0.1.53.dist-info/AUTHORS.txt
BlackBoxAuditing-0.1.53.dist-info/LICENSE.txt
BlackBoxAuditing-0.1.53.dist-info/METADATA
BlackBoxAuditing-0.1.53.dist-info/WHEEL
BlackBoxAuditing-0.1.53.dist-info/entry_points.txt
BlackBoxAuditing-0.1.53.dist-info/top_level.txt
BlackBoxAuditing-0.1.53.dist-info/RECORD
