Metadata-Version: 2.1
Name: BlackBoxAuditing
Version: 0.1.53
Summary: Sample Implementation of Gradient Feature Auditing (GFA)
Home-page: https://github.com/algofairness/BlackBoxAuditing
Author: Philip Adler, Casey Falk, Sorelle A. Friedler, Gabriel Rybeck, Carlos Scheidegger, Brandon Smith, Suresh Venkatasubramanian, Michael Feldman, John Moeller, Derek Roth, Charlie Marx
Author-email: fairness@haverford.edu
License: Apache 2.0
Keywords: algorithmic fairness
Platform: UNKNOWN
Classifier: Development Status :: 4 - Beta
Classifier: Intended Audience :: Developers
Classifier: Topic :: Software Development
Classifier: License :: OSI Approved :: Apache Software License
Classifier: Programming Language :: Python :: 2.7
Classifier: Programming Language :: Python :: 3.0
Requires-Dist: networkx
Requires-Dist: matplotlib
Requires-Dist: pandas
Requires-Dist: numpy
